{
  "configVersion": 1,
  "timestamp": 1668750972024,
  "index": "/index.html",
  "assetGroups": [
    {
      "name": "app",
      "installMode": "prefetch",
      "updateMode": "prefetch",
      "cacheQueryOptions": {
        "ignoreVary": true
      },
      "urls": [
        "/1033.4cfb0a6b0742ffec.js",
        "/1118.4d384d9dae140b02.js",
        "/1186.2d3c3f5dcbcf4ba0.js",
        "/1217.527595b8b9b47cf0.js",
        "/1536.273d389b9473875a.js",
        "/1650.2201fa6e6c656729.js",
        "/1694.a75e3cd5b6f175b3.js",
        "/1709.7f3e94eef3654804.js",
        "/174.0a6a74f63c535953.js",
        "/1877.716efd8dbd60b021.js",
        "/2073.32998d4741d3236e.js",
        "/2175.2186c18bf21b77e8.js",
        "/2289.b80bc13b1d3064e2.js",
        "/2349.22c1e7040a8a6c91.js",
        "/2698.68c89d7500d4f034.js",
        "/2744.02fcb7df7fa0fc4b.js",
        "/2773.1524ad30cb712ad3.js",
        "/3236.31df256d27a9bb38.js",
        "/3648.4d5dc90e0ad66c4f.js",
        "/3804.cbca0990c81a392e.js",
        "/388.9093993a987bfc3d.js",
        "/4174.94b1d02751b02ba3.js",
        "/4252.877b0590d010f99a.js",
        "/4330.fae8783bba576bea.js",
        "/4376.14b764670a64ba24.js",
        "/438.79dbf2ce78a114dc.js",
        "/4432.17cb9a529c3e110a.js",
        "/4564.dac9f5ad76a47f36.js",
        "/4651.3cad611de8c399a6.js",
        "/4711.cbecbbd6429a2e05.js",
        "/4753.4212c34392318161.js",
        "/4908.6437e6b66c3706c6.js",
        "/4959.a77fdfb536640bc4.js",
        "/4964.8653b051b7a26f4f.js",
        "/5168.6ffd83b15261958d.js",
        "/5349.46d22aebc32eeefc.js",
        "/5652.631e2d1b0b00adaf.js",
        "/5817.21aa1d10516e2cf3.js",
        "/5836.f9f79061383ff077.js",
        "/5950.e9531ec5d8d077ea.js",
        "/6120.9550a2679981cf05.js",
        "/6560.618b92d54aa11e6e.js",
        "/657.a4fef0abf61d8ce8.js",
        "/6718.cae742f33d6b4aae.js",
        "/7167.4199c604d8dfb572.js",
        "/7544.bc4591290a1ead04.js",
        "/7602.8ef85a856a9853d3.js",
        "/7775.9a3708cf227da000.js",
        "/8136.6a620bd7df8f11cb.js",
        "/8414.dc99b25e7599f863.js",
        "/8628.6cbe634077d0697d.js",
        "/890.5cb477fb0d67b878.js",
        "/8939.e268846754d2f8fb.js",
        "/9016.2b733f759fc50c08.js",
        "/9230.543770635d3aba68.js",
        "/9325.837d41afcbd8adf2.js",
        "/9434.93408880346b348e.js",
        "/9536.5ad2403763043257.js",
        "/9554.0777e28b194899aa.js",
        "/9654.a3af824577ea00e7.js",
        "/9824.83c2ff07be398614.js",
        "/9922.0d06e61124159c67.js",
        "/9958.2e75cfaf86f5ab8c.js",
        "/common.1a27497429f25691.js",
        "/index.html",
        "/main.030822ba206fe4fd.js",
        "/manifest.webmanifest",
        "/polyfills-core-js.cfec894cfc6a954d.js",
        "/polyfills-dom.5c5f23fb57b03028.js",
        "/polyfills.3ebd5e0cff18d293.js",
        "/runtime.81157cc15c28fea4.js",
        "/styles.feab9e19c66512c4.css"
      ],
      "patterns": []
    },
    {
      "name": "assets",
      "installMode": "lazy",
      "updateMode": "prefetch",
      "cacheQueryOptions": {
        "ignoreVary": true
      },
      "urls": [
        "/assets/i18n/en.json",
        "/assets/i18n/ko.json",
        "/assets/icon/favicon.png",
        "/assets/icons/android/android-launchericon-144-144.png",
        "/assets/icons/android/android-launchericon-192-192.png",
        "/assets/icons/android/android-launchericon-48-48.png",
        "/assets/icons/android/android-launchericon-512-512.png",
        "/assets/icons/android/android-launchericon-72-72.png",
        "/assets/icons/android/android-launchericon-96-96.png",
        "/assets/icons/ios/100.png",
        "/assets/icons/ios/1024.png",
        "/assets/icons/ios/114.png",
        "/assets/icons/ios/120.png",
        "/assets/icons/ios/128.png",
        "/assets/icons/ios/144.png",
        "/assets/icons/ios/152.png",
        "/assets/icons/ios/16.png",
        "/assets/icons/ios/167.png",
        "/assets/icons/ios/180.png",
        "/assets/icons/ios/192.png",
        "/assets/icons/ios/20.png",
        "/assets/icons/ios/256.png",
        "/assets/icons/ios/29.png",
        "/assets/icons/ios/32.png",
        "/assets/icons/ios/40.png",
        "/assets/icons/ios/50.png",
        "/assets/icons/ios/512.png",
        "/assets/icons/ios/57.png",
        "/assets/icons/ios/58.png",
        "/assets/icons/ios/60.png",
        "/assets/icons/ios/64.png",
        "/assets/icons/ios/72.png",
        "/assets/icons/ios/76.png",
        "/assets/icons/ios/80.png",
        "/assets/icons/ios/87.png",
        "/assets/icons/windows11/LargeTile.scale-100.png",
        "/assets/icons/windows11/LargeTile.scale-125.png",
        "/assets/icons/windows11/LargeTile.scale-150.png",
        "/assets/icons/windows11/LargeTile.scale-200.png",
        "/assets/icons/windows11/LargeTile.scale-400.png",
        "/assets/icons/windows11/SmallTile.scale-100.png",
        "/assets/icons/windows11/SmallTile.scale-125.png",
        "/assets/icons/windows11/SmallTile.scale-150.png",
        "/assets/icons/windows11/SmallTile.scale-200.png",
        "/assets/icons/windows11/SmallTile.scale-400.png",
        "/assets/icons/windows11/SplashScreen.scale-100.png",
        "/assets/icons/windows11/SplashScreen.scale-125.png",
        "/assets/icons/windows11/SplashScreen.scale-150.png",
        "/assets/icons/windows11/SplashScreen.scale-200.png",
        "/assets/icons/windows11/SplashScreen.scale-400.png",
        "/assets/icons/windows11/Square150x150Logo.scale-100.png",
        "/assets/icons/windows11/Square150x150Logo.scale-125.png",
        "/assets/icons/windows11/Square150x150Logo.scale-150.png",
        "/assets/icons/windows11/Square150x150Logo.scale-200.png",
        "/assets/icons/windows11/Square150x150Logo.scale-400.png",
        "/assets/icons/windows11/Square44x44Logo.altform-lightunplated_targetsize-16.png",
        "/assets/icons/windows11/Square44x44Logo.altform-lightunplated_targetsize-20.png",
        "/assets/icons/windows11/Square44x44Logo.altform-lightunplated_targetsize-24.png",
        "/assets/icons/windows11/Square44x44Logo.altform-lightunplated_targetsize-256.png",
        "/assets/icons/windows11/Square44x44Logo.altform-lightunplated_targetsize-30.png",
        "/assets/icons/windows11/Square44x44Logo.altform-lightunplated_targetsize-32.png",
        "/assets/icons/windows11/Square44x44Logo.altform-lightunplated_targetsize-36.png",
        "/assets/icons/windows11/Square44x44Logo.altform-lightunplated_targetsize-40.png",
        "/assets/icons/windows11/Square44x44Logo.altform-lightunplated_targetsize-44.png",
        "/assets/icons/windows11/Square44x44Logo.altform-lightunplated_targetsize-48.png",
        "/assets/icons/windows11/Square44x44Logo.altform-lightunplated_targetsize-60.png",
        "/assets/icons/windows11/Square44x44Logo.altform-lightunplated_targetsize-64.png",
        "/assets/icons/windows11/Square44x44Logo.altform-lightunplated_targetsize-72.png",
        "/assets/icons/windows11/Square44x44Logo.altform-lightunplated_targetsize-80.png",
        "/assets/icons/windows11/Square44x44Logo.altform-lightunplated_targetsize-96.png",
        "/assets/icons/windows11/Square44x44Logo.altform-unplated_targetsize-16.png",
        "/assets/icons/windows11/Square44x44Logo.altform-unplated_targetsize-20.png",
        "/assets/icons/windows11/Square44x44Logo.altform-unplated_targetsize-24.png",
        "/assets/icons/windows11/Square44x44Logo.altform-unplated_targetsize-256.png",
        "/assets/icons/windows11/Square44x44Logo.altform-unplated_targetsize-30.png",
        "/assets/icons/windows11/Square44x44Logo.altform-unplated_targetsize-32.png",
        "/assets/icons/windows11/Square44x44Logo.altform-unplated_targetsize-36.png",
        "/assets/icons/windows11/Square44x44Logo.altform-unplated_targetsize-40.png",
        "/assets/icons/windows11/Square44x44Logo.altform-unplated_targetsize-44.png",
        "/assets/icons/windows11/Square44x44Logo.altform-unplated_targetsize-48.png",
        "/assets/icons/windows11/Square44x44Logo.altform-unplated_targetsize-60.png",
        "/assets/icons/windows11/Square44x44Logo.altform-unplated_targetsize-64.png",
        "/assets/icons/windows11/Square44x44Logo.altform-unplated_targetsize-72.png",
        "/assets/icons/windows11/Square44x44Logo.altform-unplated_targetsize-80.png",
        "/assets/icons/windows11/Square44x44Logo.altform-unplated_targetsize-96.png",
        "/assets/icons/windows11/Square44x44Logo.scale-100.png",
        "/assets/icons/windows11/Square44x44Logo.scale-125.png",
        "/assets/icons/windows11/Square44x44Logo.scale-150.png",
        "/assets/icons/windows11/Square44x44Logo.scale-200.png",
        "/assets/icons/windows11/Square44x44Logo.scale-400.png",
        "/assets/icons/windows11/Square44x44Logo.targetsize-16.png",
        "/assets/icons/windows11/Square44x44Logo.targetsize-20.png",
        "/assets/icons/windows11/Square44x44Logo.targetsize-24.png",
        "/assets/icons/windows11/Square44x44Logo.targetsize-256.png",
        "/assets/icons/windows11/Square44x44Logo.targetsize-30.png",
        "/assets/icons/windows11/Square44x44Logo.targetsize-32.png",
        "/assets/icons/windows11/Square44x44Logo.targetsize-36.png",
        "/assets/icons/windows11/Square44x44Logo.targetsize-40.png",
        "/assets/icons/windows11/Square44x44Logo.targetsize-44.png",
        "/assets/icons/windows11/Square44x44Logo.targetsize-48.png",
        "/assets/icons/windows11/Square44x44Logo.targetsize-60.png",
        "/assets/icons/windows11/Square44x44Logo.targetsize-64.png",
        "/assets/icons/windows11/Square44x44Logo.targetsize-72.png",
        "/assets/icons/windows11/Square44x44Logo.targetsize-80.png",
        "/assets/icons/windows11/Square44x44Logo.targetsize-96.png",
        "/assets/icons/windows11/StoreLogo.scale-100.png",
        "/assets/icons/windows11/StoreLogo.scale-125.png",
        "/assets/icons/windows11/StoreLogo.scale-150.png",
        "/assets/icons/windows11/StoreLogo.scale-200.png",
        "/assets/icons/windows11/StoreLogo.scale-400.png",
        "/assets/icons/windows11/Wide310x150Logo.scale-100.png",
        "/assets/icons/windows11/Wide310x150Logo.scale-125.png",
        "/assets/icons/windows11/Wide310x150Logo.scale-150.png",
        "/assets/icons/windows11/Wide310x150Logo.scale-200.png",
        "/assets/icons/windows11/Wide310x150Logo.scale-400.png",
        "/assets/shapes.svg"
      ],
      "patterns": []
    }
  ],
  "dataGroups": [],
  "hashTable": {
    "/1033.4cfb0a6b0742ffec.js": "bd139168ecb0556f2b05472979666dd2b4b52eac",
    "/1118.4d384d9dae140b02.js": "e4bfeb87b659a7fb34fc95d45739d66f84239476",
    "/1186.2d3c3f5dcbcf4ba0.js": "49000580ad271c2734bcef5801813a377f3a6ae3",
    "/1217.527595b8b9b47cf0.js": "5ba7d6272d0d6db7e2e45863e4eae19910ae0220",
    "/1536.273d389b9473875a.js": "8510db5dafc907a46fc49c013420787c43c9f9a4",
    "/1650.2201fa6e6c656729.js": "92070b0198c9a8a4b15c3d3707c2cedd98f7f249",
    "/1694.a75e3cd5b6f175b3.js": "82d2442c6598cae371b182c4b417be524686cf8d",
    "/1709.7f3e94eef3654804.js": "439291e9179c8da9adad6f753a76f7192b1344bb",
    "/174.0a6a74f63c535953.js": "736c335dd75ae93dec460eab906c4071f89fc84f",
    "/1877.716efd8dbd60b021.js": "34475c0d0c2ff8648bb4803dbc8308b3ccc76057",
    "/2073.32998d4741d3236e.js": "667fdd3b5cab2e401c24744a2ab4801b3503a0e1",
    "/2175.2186c18bf21b77e8.js": "d615e065efbf417df4cdf0b14aea9aa5db9b06ff",
    "/2289.b80bc13b1d3064e2.js": "ba6f01cdade38bf2c49a2d58a22d86cb06ffac65",
    "/2349.22c1e7040a8a6c91.js": "ae458dc2d7c3e2c048d56a3bb1e0e2f351dd4b4f",
    "/2698.68c89d7500d4f034.js": "8813a9f5144ffb733157b1730c3f3bf66d00a9b5",
    "/2744.02fcb7df7fa0fc4b.js": "3333996ae83f2ff73f9b7e59837c1a0dea2b3bc1",
    "/2773.1524ad30cb712ad3.js": "04bd357d67c76ad178feb08fca7f0748f094416c",
    "/3236.31df256d27a9bb38.js": "9691d670a38d9c84f890c9d6a60f79ae693e8a84",
    "/3648.4d5dc90e0ad66c4f.js": "287423e0ac37666d0fddbc7d0b107e577bac8d13",
    "/3804.cbca0990c81a392e.js": "9ae798a4ef0a4d02f85033c787e5f00bc6eb0a6d",
    "/388.9093993a987bfc3d.js": "70d2d20406e2673ad1e54e9079551d7273d7efb3",
    "/4174.94b1d02751b02ba3.js": "c48a0d7be5daf7493847245496484ce702130d88",
    "/4252.877b0590d010f99a.js": "a2549dfd03e4bb91da4456c0a4fa814c8b2540da",
    "/4330.fae8783bba576bea.js": "d5b1004611ce7503df84c6593fcdee53c83aa654",
    "/4376.14b764670a64ba24.js": "e0f98efa5655694f3b617d29252675ea81851fd7",
    "/438.79dbf2ce78a114dc.js": "f65879e196b4317707f007c68df4205f9345e984",
    "/4432.17cb9a529c3e110a.js": "65235b776b1c4730842e6ec437d07b0307b69c0d",
    "/4564.dac9f5ad76a47f36.js": "597ab1cb20d5c83920d2f65d352fb038b5489b36",
    "/4651.3cad611de8c399a6.js": "28edd55f1f7b13f3b51136dd4d1efaf4fd0cd9a2",
    "/4711.cbecbbd6429a2e05.js": "1efb82b66ed6638d3c6fb8779d2e37732915932c",
    "/4753.4212c34392318161.js": "0d5060bd280d2eef98fb06f514b59c4f3946e8cd",
    "/4908.6437e6b66c3706c6.js": "6f113786d4cac4e490008b7d4aba3c0d8e9628ef",
    "/4959.a77fdfb536640bc4.js": "612a83467be0d66798e3f1e68cf5974b68831170",
    "/4964.8653b051b7a26f4f.js": "47442d9de1adf56cf2d3839490c019e63c610fa7",
    "/5168.6ffd83b15261958d.js": "9b787f98f1c8aa9c00aecceb6e89ccd65aa16b31",
    "/5349.46d22aebc32eeefc.js": "d9cc772bce4bf499605666d34beb0e0e067dd3fb",
    "/5652.631e2d1b0b00adaf.js": "6260dc2d9d221903910e560879f2552bd63859bd",
    "/5817.21aa1d10516e2cf3.js": "278edac72396fca46c04a79faa22d91e04223fb1",
    "/5836.f9f79061383ff077.js": "6e3f3ef7b06e7dc405e7735522931c3ef891beb0",
    "/5950.e9531ec5d8d077ea.js": "292a7b3964df3318e0fd84f123a6b4329c382aab",
    "/6120.9550a2679981cf05.js": "6e5a3ea17994b1d7f67c10968517e9febfd05ca6",
    "/6560.618b92d54aa11e6e.js": "b28fa4b93ff4cc9a7fa0bc5e658bb4ef6fad8109",
    "/657.a4fef0abf61d8ce8.js": "4bcd87abf527d444771ba1c7536bd16bf630f92d",
    "/6718.cae742f33d6b4aae.js": "063d39815bb17bfb8cb8ba107487a54eac00ad7b",
    "/7167.4199c604d8dfb572.js": "7c4d96d58d28ac58d15085d6d1e0a9b4541f5d1f",
    "/7544.bc4591290a1ead04.js": "7ebe1bca77029a546cb855f5d52327d80b2a6153",
    "/7602.8ef85a856a9853d3.js": "0b40c33177036153c6b3d6555135ecfcc2c78ea0",
    "/7775.9a3708cf227da000.js": "2161e3239139e9a02e6959dd7bad37cec9fce493",
    "/8136.6a620bd7df8f11cb.js": "56e914af9c61df2f952ef6c8614cf39b5936f67f",
    "/8414.dc99b25e7599f863.js": "30cd99692a65a00abce337a4f7b195e958ac3b3a",
    "/8628.6cbe634077d0697d.js": "facbff8139188fccc8e80c9935c01ada02ef91b1",
    "/890.5cb477fb0d67b878.js": "5680f0599f4f480ca511f2c191f815cdd99f522d",
    "/8939.e268846754d2f8fb.js": "a24672312feb75b36d60d5eca2bc30281416b4c0",
    "/9016.2b733f759fc50c08.js": "8448e6c0273bb71ce782d76fd7e18ffeaaa989d0",
    "/9230.543770635d3aba68.js": "b3da8f6094c9518ab8df4cdc32abcb82a1ed6c11",
    "/9325.837d41afcbd8adf2.js": "9c6f8b5fb55a5221a11a8b6d8c9dae20e83698d5",
    "/9434.93408880346b348e.js": "8c2501993e03633cd9266fa81946269e409bdb13",
    "/9536.5ad2403763043257.js": "5dc9438c29762182172514dc164a2417a05ba7d3",
    "/9554.0777e28b194899aa.js": "c3f78afe943e1611b23f88446f57ea3b0189ad49",
    "/9654.a3af824577ea00e7.js": "497a8e5ae3068e2d3605d1351cd8488f49810cee",
    "/9824.83c2ff07be398614.js": "710a78711d3ffde17d7b0c286fb250c08acaa72c",
    "/9922.0d06e61124159c67.js": "e53b0f70ac3a44baddae58ee5a34a4ed6bde054a",
    "/9958.2e75cfaf86f5ab8c.js": "fe09c9be181b2bdaabec4b179d6fd01528711e1e",
    "/assets/i18n/en.json": "6054de0f4d2e3641c4e4b9be5de053951291ae77",
    "/assets/i18n/ko.json": "a5feaaadef3e735efd499f4fa813691326f6bd8b",
    "/assets/icon/favicon.png": "7798b8e0eb61d7375c245af78bbf5c916932bf13",
    "/assets/icons/android/android-launchericon-144-144.png": "dfc267062b5eb2253a42fa9d0c01afdcd4a46387",
    "/assets/icons/android/android-launchericon-192-192.png": "115ad3b8f79fa0bbd2ac3a2f30ef584c64f58539",
    "/assets/icons/android/android-launchericon-48-48.png": "b6e5b65616499f1514af5980302bb5f829c286f5",
    "/assets/icons/android/android-launchericon-512-512.png": "927bd5804975fb22ff12191e95453b47afb282e8",
    "/assets/icons/android/android-launchericon-72-72.png": "4e0b61635783b2b9c41bbc73733ffae1b2b53b82",
    "/assets/icons/android/android-launchericon-96-96.png": "255db33b0f6bbc452b834e419e78cfbdd203014b",
    "/assets/icons/ios/100.png": "b55028bf4964657fe0b88a784f597bf66b5d0d93",
    "/assets/icons/ios/1024.png": "3a1fd8b58bfd24f16a9da37c0abff55606aa1d8c",
    "/assets/icons/ios/114.png": "b3f8ccf125df298a2702fee74a027d93b08f90b7",
    "/assets/icons/ios/120.png": "12bcda8a677196fc303bc3c9e1e76bf3da2e8161",
    "/assets/icons/ios/128.png": "95c49b6788246a770235618794793a6423053344",
    "/assets/icons/ios/144.png": "dfc267062b5eb2253a42fa9d0c01afdcd4a46387",
    "/assets/icons/ios/152.png": "d549797bbacf850ae0a45e92bfaffc68e6bfe614",
    "/assets/icons/ios/16.png": "857869261c89cd31812fbff6ee032ef92f176b02",
    "/assets/icons/ios/167.png": "f655de1d049e11c1abfa7e647c952935b8300829",
    "/assets/icons/ios/180.png": "aa1d8c00ec835a1ba99e109104cb5929b012c025",
    "/assets/icons/ios/192.png": "115ad3b8f79fa0bbd2ac3a2f30ef584c64f58539",
    "/assets/icons/ios/20.png": "759b2d2268e092e02fda718243be641c73530bdb",
    "/assets/icons/ios/256.png": "e51342e58bb62180ad68cd4bfa3f2fcbc6a2c409",
    "/assets/icons/ios/29.png": "24bf92c83158eb68a7ee758965655608401f16b6",
    "/assets/icons/ios/32.png": "31711b422bd7d30aa569235029baca4bb71a490f",
    "/assets/icons/ios/40.png": "ceefb48e0fed9af4d07b033f02e95b212f21ac89",
    "/assets/icons/ios/50.png": "b0f1129c2ec23ee852e7963f9b399f99fa663618",
    "/assets/icons/ios/512.png": "927bd5804975fb22ff12191e95453b47afb282e8",
    "/assets/icons/ios/57.png": "3684fc12ebcae992e0f380920671debeb6e4255b",
    "/assets/icons/ios/58.png": "021b20e4ce528577ef72c1baa7b17bc800484b52",
    "/assets/icons/ios/60.png": "2fce8d4d01150117524df7c38826b70adf15b7c0",
    "/assets/icons/ios/64.png": "8a0bb0f4959aeceb1af2c10cc0eef4d12d1b9e20",
    "/assets/icons/ios/72.png": "4e0b61635783b2b9c41bbc73733ffae1b2b53b82",
    "/assets/icons/ios/76.png": "152f1e458b513864ae95f47b5feb88964fe77397",
    "/assets/icons/ios/80.png": "08185890bbe3297a969b7e6a6e6fb78690083e10",
    "/assets/icons/ios/87.png": "bd8a3af65f2a6ea62d8ffd4993d3f1578c8f0f55",
    "/assets/icons/windows11/LargeTile.scale-100.png": "939f694d6d0e7de334bc9a9a61170b6f0d5ea6e6",
    "/assets/icons/windows11/LargeTile.scale-125.png": "20a14faeb5bf63f0bdee874d8852f0dd1810bf91",
    "/assets/icons/windows11/LargeTile.scale-150.png": "88bf33eb873aefda0094b3510e8a90898be943c5",
    "/assets/icons/windows11/LargeTile.scale-200.png": "bbdb60d933e6e43e36832538c2aac361280db574",
    "/assets/icons/windows11/LargeTile.scale-400.png": "76d0a7bfbc940c96e84be5524e0cf4aeea090fb0",
    "/assets/icons/windows11/SmallTile.scale-100.png": "de1c4731a178a34c43c6e5b3ee1292f22548fb9c",
    "/assets/icons/windows11/SmallTile.scale-125.png": "9de0095241468161a39ca1a2bdb9f39f23decd4b",
    "/assets/icons/windows11/SmallTile.scale-150.png": "f6dbab497200ac7c10279035ecb6b2bdf8ced441",
    "/assets/icons/windows11/SmallTile.scale-200.png": "0f98a32f70b2aa4b178f4ae51e754f0062dc1a77",
    "/assets/icons/windows11/SmallTile.scale-400.png": "b38ba3b4cd6e08a4017180a99eef6e75a0aa6f5b",
    "/assets/icons/windows11/SplashScreen.scale-100.png": "6bb3d8a174e466f8ab2deae0d6cc38894c4869f3",
    "/assets/icons/windows11/SplashScreen.scale-125.png": "6d46f6c78ab0b9f87155debcaad3f8115969ca1c",
    "/assets/icons/windows11/SplashScreen.scale-150.png": "21ef4cd15e6fc0e2d2b48bc6414829cff58864e8",
    "/assets/icons/windows11/SplashScreen.scale-200.png": "abde4540f7e64603ae542c40b68fee35198ff1ae",
    "/assets/icons/windows11/SplashScreen.scale-400.png": "d5236d42573701e61380411bf3c0f8d485e52f1e",
    "/assets/icons/windows11/Square150x150Logo.scale-100.png": "dfa67afa77e354907c415d339c79ae9e1b108f67",
    "/assets/icons/windows11/Square150x150Logo.scale-125.png": "ca19bf04b414e98444477a2c9c7f1387dbf927c4",
    "/assets/icons/windows11/Square150x150Logo.scale-150.png": "f3db55ce5d9dbb7a5dd02a6c9ffc36ad8cef8517",
    "/assets/icons/windows11/Square150x150Logo.scale-200.png": "660423cd2f159869ebff56316113ba76fec05dfb",
    "/assets/icons/windows11/Square150x150Logo.scale-400.png": "96f1b2dbf3585b77b3f3e86d4494f5c038dd56cd",
    "/assets/icons/windows11/Square44x44Logo.altform-lightunplated_targetsize-16.png": "46a6caef6a24d4f627ccffc134e83060836dfbd7",
    "/assets/icons/windows11/Square44x44Logo.altform-lightunplated_targetsize-20.png": "04e78875626492cc74a7abdae226250d4e3a2736",
    "/assets/icons/windows11/Square44x44Logo.altform-lightunplated_targetsize-24.png": "0c6e10a92bb1ac1f1db816cf13a2d4497cc454f8",
    "/assets/icons/windows11/Square44x44Logo.altform-lightunplated_targetsize-256.png": "5bb20bcf27e6979fd4aa8b872ce289f80135eed4",
    "/assets/icons/windows11/Square44x44Logo.altform-lightunplated_targetsize-30.png": "59e81a0f88f90f6e61d9b5e57c7ebb671a1b7dec",
    "/assets/icons/windows11/Square44x44Logo.altform-lightunplated_targetsize-32.png": "a7dfd137ecd19ae45ee72804c445ae39ce4431ad",
    "/assets/icons/windows11/Square44x44Logo.altform-lightunplated_targetsize-36.png": "753a7179a2aa3ee4d238fe4add5a2ee9aa776a42",
    "/assets/icons/windows11/Square44x44Logo.altform-lightunplated_targetsize-40.png": "5b9608b3f4a72bdbd73bbb303d57d92b9591b59d",
    "/assets/icons/windows11/Square44x44Logo.altform-lightunplated_targetsize-44.png": "3f3a3a1e42ed704b4ef3fab386d5084ba64241a9",
    "/assets/icons/windows11/Square44x44Logo.altform-lightunplated_targetsize-48.png": "99fba7ee6db114f5ab499b8b34fc85ed4d6ab4d3",
    "/assets/icons/windows11/Square44x44Logo.altform-lightunplated_targetsize-60.png": "2eaafe6f7a6ab74cd4ecda253c34555295401ba0",
    "/assets/icons/windows11/Square44x44Logo.altform-lightunplated_targetsize-64.png": "d35e94cca9178f19c13f6e65fb9704313eb06f46",
    "/assets/icons/windows11/Square44x44Logo.altform-lightunplated_targetsize-72.png": "9c342b00c936c6bdac8e4f0a182b1e0c01343124",
    "/assets/icons/windows11/Square44x44Logo.altform-lightunplated_targetsize-80.png": "c6e70bf1ec854e60b4ee114642ba6ef00a0214ac",
    "/assets/icons/windows11/Square44x44Logo.altform-lightunplated_targetsize-96.png": "a1020e4c06ec143707865e6111dd165150bce622",
    "/assets/icons/windows11/Square44x44Logo.altform-unplated_targetsize-16.png": "46a6caef6a24d4f627ccffc134e83060836dfbd7",
    "/assets/icons/windows11/Square44x44Logo.altform-unplated_targetsize-20.png": "04e78875626492cc74a7abdae226250d4e3a2736",
    "/assets/icons/windows11/Square44x44Logo.altform-unplated_targetsize-24.png": "0c6e10a92bb1ac1f1db816cf13a2d4497cc454f8",
    "/assets/icons/windows11/Square44x44Logo.altform-unplated_targetsize-256.png": "5bb20bcf27e6979fd4aa8b872ce289f80135eed4",
    "/assets/icons/windows11/Square44x44Logo.altform-unplated_targetsize-30.png": "59e81a0f88f90f6e61d9b5e57c7ebb671a1b7dec",
    "/assets/icons/windows11/Square44x44Logo.altform-unplated_targetsize-32.png": "a7dfd137ecd19ae45ee72804c445ae39ce4431ad",
    "/assets/icons/windows11/Square44x44Logo.altform-unplated_targetsize-36.png": "753a7179a2aa3ee4d238fe4add5a2ee9aa776a42",
    "/assets/icons/windows11/Square44x44Logo.altform-unplated_targetsize-40.png": "5b9608b3f4a72bdbd73bbb303d57d92b9591b59d",
    "/assets/icons/windows11/Square44x44Logo.altform-unplated_targetsize-44.png": "3f3a3a1e42ed704b4ef3fab386d5084ba64241a9",
    "/assets/icons/windows11/Square44x44Logo.altform-unplated_targetsize-48.png": "99fba7ee6db114f5ab499b8b34fc85ed4d6ab4d3",
    "/assets/icons/windows11/Square44x44Logo.altform-unplated_targetsize-60.png": "2eaafe6f7a6ab74cd4ecda253c34555295401ba0",
    "/assets/icons/windows11/Square44x44Logo.altform-unplated_targetsize-64.png": "d35e94cca9178f19c13f6e65fb9704313eb06f46",
    "/assets/icons/windows11/Square44x44Logo.altform-unplated_targetsize-72.png": "9c342b00c936c6bdac8e4f0a182b1e0c01343124",
    "/assets/icons/windows11/Square44x44Logo.altform-unplated_targetsize-80.png": "c6e70bf1ec854e60b4ee114642ba6ef00a0214ac",
    "/assets/icons/windows11/Square44x44Logo.altform-unplated_targetsize-96.png": "a1020e4c06ec143707865e6111dd165150bce622",
    "/assets/icons/windows11/Square44x44Logo.scale-100.png": "3f3a3a1e42ed704b4ef3fab386d5084ba64241a9",
    "/assets/icons/windows11/Square44x44Logo.scale-125.png": "1d9958b1eb9aae00cd7a11a1dddc89e83d12e0b0",
    "/assets/icons/windows11/Square44x44Logo.scale-150.png": "c51b1ccb23db97869fbcd23ce7b9dc92a0bd8e05",
    "/assets/icons/windows11/Square44x44Logo.scale-200.png": "eb1e5fff440a8014538bc1303160996fbe1c19d1",
    "/assets/icons/windows11/Square44x44Logo.scale-400.png": "76d37e535376a93cc47298fc85ddbc4052424aae",
    "/assets/icons/windows11/Square44x44Logo.targetsize-16.png": "46a6caef6a24d4f627ccffc134e83060836dfbd7",
    "/assets/icons/windows11/Square44x44Logo.targetsize-20.png": "04e78875626492cc74a7abdae226250d4e3a2736",
    "/assets/icons/windows11/Square44x44Logo.targetsize-24.png": "0c6e10a92bb1ac1f1db816cf13a2d4497cc454f8",
    "/assets/icons/windows11/Square44x44Logo.targetsize-256.png": "5bb20bcf27e6979fd4aa8b872ce289f80135eed4",
    "/assets/icons/windows11/Square44x44Logo.targetsize-30.png": "59e81a0f88f90f6e61d9b5e57c7ebb671a1b7dec",
    "/assets/icons/windows11/Square44x44Logo.targetsize-32.png": "a7dfd137ecd19ae45ee72804c445ae39ce4431ad",
    "/assets/icons/windows11/Square44x44Logo.targetsize-36.png": "753a7179a2aa3ee4d238fe4add5a2ee9aa776a42",
    "/assets/icons/windows11/Square44x44Logo.targetsize-40.png": "5b9608b3f4a72bdbd73bbb303d57d92b9591b59d",
    "/assets/icons/windows11/Square44x44Logo.targetsize-44.png": "3f3a3a1e42ed704b4ef3fab386d5084ba64241a9",
    "/assets/icons/windows11/Square44x44Logo.targetsize-48.png": "99fba7ee6db114f5ab499b8b34fc85ed4d6ab4d3",
    "/assets/icons/windows11/Square44x44Logo.targetsize-60.png": "2eaafe6f7a6ab74cd4ecda253c34555295401ba0",
    "/assets/icons/windows11/Square44x44Logo.targetsize-64.png": "d35e94cca9178f19c13f6e65fb9704313eb06f46",
    "/assets/icons/windows11/Square44x44Logo.targetsize-72.png": "9c342b00c936c6bdac8e4f0a182b1e0c01343124",
    "/assets/icons/windows11/Square44x44Logo.targetsize-80.png": "c6e70bf1ec854e60b4ee114642ba6ef00a0214ac",
    "/assets/icons/windows11/Square44x44Logo.targetsize-96.png": "a1020e4c06ec143707865e6111dd165150bce622",
    "/assets/icons/windows11/StoreLogo.scale-100.png": "b0f1129c2ec23ee852e7963f9b399f99fa663618",
    "/assets/icons/windows11/StoreLogo.scale-125.png": "cf93c9a29ff227e8b8a873f10445b82330e4030c",
    "/assets/icons/windows11/StoreLogo.scale-150.png": "d567daf5dabd31845decb5ce8ce1b813059dca42",
    "/assets/icons/windows11/StoreLogo.scale-200.png": "b55028bf4964657fe0b88a784f597bf66b5d0d93",
    "/assets/icons/windows11/StoreLogo.scale-400.png": "6160c4e67863a874549ac7be18dd468fa7816ce8",
    "/assets/icons/windows11/Wide310x150Logo.scale-100.png": "c942fed5f7ed981986fa6d5f02ce97ffb3285225",
    "/assets/icons/windows11/Wide310x150Logo.scale-125.png": "855b98da52bb3bfd57b53eeda704f2f6dedf65dc",
    "/assets/icons/windows11/Wide310x150Logo.scale-150.png": "9124adf0ff0d4505934de17ff8cb5cd14be676aa",
    "/assets/icons/windows11/Wide310x150Logo.scale-200.png": "6bb3d8a174e466f8ab2deae0d6cc38894c4869f3",
    "/assets/icons/windows11/Wide310x150Logo.scale-400.png": "abde4540f7e64603ae542c40b68fee35198ff1ae",
    "/assets/shapes.svg": "5413e95adabcb2cb639970051f55e0ddb64ace53",
    "/common.1a27497429f25691.js": "8271b0b52b7766d167ab2cc098a88a163546da3b",
    "/index.html": "c6e5569cbbbb58595c4133b23a15c3738084c276",
    "/main.030822ba206fe4fd.js": "58b563b157b26628401c6cd84d6b8910b08be7e3",
    "/manifest.webmanifest": "13d0b71184b6802c8a6a3d259314cb381ea00b84",
    "/polyfills-core-js.cfec894cfc6a954d.js": "2d5536082087325c25c99545e29ac3abb39e4cc9",
    "/polyfills-dom.5c5f23fb57b03028.js": "06f5dc30f55bf9a3d9c6f9bca07c0041a6bbdaa0",
    "/polyfills.3ebd5e0cff18d293.js": "a4f03ad9599028ce006f4ac1ee55c63d4370a70b",
    "/runtime.81157cc15c28fea4.js": "16244da64ccd2c8b988933114bde20e051bba00c",
    "/styles.feab9e19c66512c4.css": "8a3a6796ddc655669da5be054abb891a7832d99f"
  },
  "navigationUrls": [
    {
      "positive": true,
      "regex": "^\\/.*$"
    },
    {
      "positive": false,
      "regex": "^\\/(?:.+\\/)?[^/]*\\.[^/]*$"
    },
    {
      "positive": false,
      "regex": "^\\/(?:.+\\/)?[^/]*__[^/]*$"
    },
    {
      "positive": false,
      "regex": "^\\/(?:.+\\/)?[^/]*__[^/]*\\/.*$"
    }
  ],
  "navigationRequestStrategy": "performance"
}